{
  "version": "7",
  "dialect": "postgresql",
  "entries": [
    {
      "idx": 0,
      "version": "7",
      "when": 1775543164664,
      "tag": "0000_cuddly_legion",
      "breakpoints": true
    },
    {
      "idx": 1,
      "version": "7",
      "when": 1775744764264,
      "tag": "0001_require_approval",
      "breakpoints": true
    },
    {
      "idx": 2,
      "version": "7",
      "when": 1775747213270,
      "tag": "0002_pending_invites",
      "breakpoints": true
    },
    {
      "idx": 3,
      "version": "7",
      "when": 1781590297424,
      "tag": "0003_unknown_daredevil",
      "breakpoints": true
    },
    {
      "idx": 4,
      "version": "7",
      "when": 1781718342132,
      "tag": "0004_perf_indexes",
      "breakpoints": true
    },
    {
      "idx": 5,
      "version": "7",
      "when": 1781746817649,
      "tag": "0005_ancient_jack_flag",
      "breakpoints": true
    },
    {
      "idx": 6,
      "version": "7",
      "when": 1781772312285,
      "tag": "0006_far_magik",
      "breakpoints": true
    },
    {
      "idx": 7,
      "version": "7",
      "when": 1781786193832,
      "tag": "0007_square_ulik",
      "breakpoints": true
    },
    {
      "idx": 8,
      "version": "7",
      "when": 1781965331188,
      "tag": "0008_powerful_daredevil",
      "breakpoints": true
    },
    {
      "idx": 9,
      "version": "7",
      "when": 1782045101489,
      "tag": "0009_cuddly_makkari",
      "breakpoints": true
    },
    {
      "idx": 10,
      "version": "7",
      "when": 1782094141499,
      "tag": "0010_majestic_havok",
      "breakpoints": true
    },
    {
      "idx": 11,
      "version": "7",
      "when": 1782172910127,
      "tag": "0011_chemical_squadron_sinister",
      "breakpoints": true
    },
    {
      "idx": 12,
      "version": "7",
      "when": 1782210806302,
      "tag": "0012_parallel_spencer_smythe",
      "breakpoints": true
    }
  ]
}